salling_group_holidays/__init__.py
salling_group_holidays/api.py
salling_group_holidays-0.4.dist-info/LICENSE
salling_group_holidays-0.4.dist-info/METADATA
salling_group_holidays-0.4.dist-info/WHEEL
salling_group_holidays-0.4.dist-info/top_level.txt
salling_group_holidays-0.4.dist-info/RECORD
