Metadata-Version: 2.1
Name: salling-group-holidays
Version: 0.4
Summary: Unofficial library for the Salling Group holidays API
Home-page: https://github.com/laudrup/salling-group-holidays
Author: Kasper Laudrup
Author-email: laudrup@stacktrace.dk
License: MIT
Keywords: holidays,calendar,salling,denmark,danish
Platform: UNKNOWN
Classifier: Development Status :: 4 - Beta
Classifier: License :: OSI Approved :: MIT License
Classifier: Operating System :: POSIX :: Linux
Classifier: Operating System :: Microsoft :: Windows
Classifier: Programming Language :: Python :: 3 :: Only
Classifier: Programming Language :: Python :: 3.4
Classifier: Programming Language :: Python :: 3.5
Classifier: Programming Language :: Python :: 3.6
Classifier: Topic :: Software Development :: Libraries
Requires-Dist: requests
Requires-Dist: wheel
